{"title": "\u5287\u5834\u7248\u300cFate/stay night [HF]\u300d\u7b2c\uff12\u5f3e", "id": "Fate_stay_night_Heavens_Feelvol.2", "stickers": [{"body": "349561750", "url": "mxc://seanpai.dev/RKmXzGynweYytTKADWhKRgUS", "info": {"w": 256, "h": 213, "size": 177989, "mimetype": "image/png", "thumbnail_url": "mxc://seanpai.dev/RKmXzGynweYytTKADWhKRgUS", "thumbnail_info": {"w": 256, "h": 213, "size": 177989, "mimetype": "image/png"}}, "msgtype": "m.sticker", "id": "sha256:955d817409da330042d4640ef3d424ce8678ac0c792f812938bc4e0fd2ad6c0b"}, {"body": "349561751", "url": "mxc://seanpai.dev/IMZZKnZHiySdMgNOBJMxoKgH", "info": {"w": 256, "h": 201, "size": 141023, "mimetype": "image/png", "thumbnail_url": "mxc://seanpai.dev/IMZZKnZHiySdMgNOBJMxoKgH", "thumbnail_info": {"w": 256, "h": 201, "size": 141023, "mimetype": "image/png"}}, "msgtype": "m.sticker", "id": "sha256:1b89afc7a5d1bc6727e7d97116b8e052639ab552832620c461bebc8eb43a9d59"}, {"body": "349561752", "url": "mxc://seanpai.dev/GOyMUsVMCsUGdCmbmTLrvCyf", "info": {"w": 256, "h": 213, "size": 186802, "mimetype": "image/png", "thumbnail_url": "mxc://seanpai.dev/GOyMUsVMCsUGdCmbmTLrvCyf", "thumbnail_info": {"w": 256, "h": 213, "size": 186802, "mimetype": "image/png"}}, "msgtype": "m.sticker", "id": "sha256:5a2aedf54667b0046a76818130b9b4e62074fc1dcd1c951f696179ae34450cc7"}, {"body": "349561753", "url": "mxc://seanpai.dev/IMKLOnYnYhKNwQFeaQUmOQtQ", "info": {"w": 256, "h": 188, "size": 132800, "mimetype": "image/png", "thumbnail_url": "mxc://seanpai.dev/IMKLOnYnYhKNwQFeaQUmOQtQ", "thumbnail_info": {"w": 256, "h": 188, "size": 132800, "mimetype": "image/png"}}, "msgtype": "m.sticker", "id": "sha256:2e1ee4a666aecb0f59d649087f98c8b2d7bb12ac473ef61a13d05c918cb10d1a"}, {"body": "349561754", "url": "mxc://seanpai.dev/QuYYHzJGGddIxaRmOPbPIrHt", "info": {"w": 256, "h": 201, "size": 100367, "mimetype": "image/png", "thumbnail_url": "mxc://seanpai.dev/QuYYHzJGGddIxaRmOPbPIrHt", "thumbnail_info": {"w": 256, "h": 201, "size": 100367, "mimetype": "image/png"}}, "msgtype": "m.sticker", "id": "sha256:ad7887df948578894b7c40634ca31aa6a7de782b1205985d41c8414bc2d42b7e"}, {"body": "349561755", "url": "mxc://seanpai.dev/QLRrbvvGkvVExBoZiFDTpOJs", "info": {"w": 256, "h": 188, "size": 127385, "mimetype": "image/png", "thumbnail_url": "mxc://seanpai.dev/QLRrbvvGkvVExBoZiFDTpOJs", "thumbnail_info": {"w": 256, "h": 188, "size": 127385, "mimetype": "image/png"}}, "msgtype": "m.sticker", "id": "sha256:e918e23530f35add79bf42ca668898f2d5c28ca95c6138e87ccb922e51e5f8ce"}, {"body": "349561756", "url": "mxc://seanpai.dev/PljFqAgaJNbbZFTgDafeknVU", "info": {"w": 256, "h": 214, "size": 128616, "mimetype": "image/png", "thumbnail_url": "mxc://seanpai.dev/PljFqAgaJNbbZFTgDafeknVU", "thumbnail_info": {"w": 256, "h": 214, "size": 128616, "mimetype": "image/png"}}, "msgtype": "m.sticker", "id": "sha256:083c1adcc257947f2168f245316cb7747d3b7c8d61dd4925f023740773912586"}, {"body": "349561757", "url": "mxc://seanpai.dev/iLSwUxFpaMkuRlTvYUYlbnMf", "info": {"w": 256, "h": 213, "size": 156427, "mimetype": "image/png", "thumbnail_url": "mxc://seanpai.dev/iLSwUxFpaMkuRlTvYUYlbnMf", "thumbnail_info": {"w": 256, "h": 213, "size": 156427, "mimetype": "image/png"}}, "msgtype": "m.sticker", "id": "sha256:7f3ada6e0a5c417c1260b3e14fdedf8a9891ea6746c1ef9a9a65d5610b5fbd43"}, {"body": "349561758", "url": "mxc://seanpai.dev/hKIOzRXitiGruEdFJNEuMWUE", "info": {"w": 256, "h": 216, "size": 105324, "mimetype": "image/png", "thumbnail_url": "mxc://seanpai.dev/hKIOzRXitiGruEdFJNEuMWUE", "thumbnail_info": {"w": 256, "h": 216, "size": 105324, "mimetype": "image/png"}}, "msgtype": "m.sticker", "id": "sha256:6df5239a0723cba38ec63f36302d2ad92691d6eab044a2082480fb965eafea75"}, {"body": "349561759", "url": "mxc://seanpai.dev/dyhyenOFImLnjXoOkXUgcMPV", "info": {"w": 256, "h": 214, "size": 140420, "mimetype": "image/png", "thumbnail_url": "mxc://seanpai.dev/dyhyenOFImLnjXoOkXUgcMPV", "thumbnail_info": {"w": 256, "h": 214, "size": 140420, "mimetype": "image/png"}}, "msgtype": "m.sticker", "id": "sha256:6265b5dc45814f1954648f04cd8ad9bcfe07ebb591701d1086272b5703d360a1"}, {"body": "349561760", "url": "mxc://seanpai.dev/yJNswTwJiQWNOFNBDbmmUpkZ", "info": {"w": 256, "h": 213, "size": 123455, "mimetype": "image/png", "thumbnail_url": "mxc://seanpai.dev/yJNswTwJiQWNOFNBDbmmUpkZ", "thumbnail_info": {"w": 256, "h": 213, "size": 123455, "mimetype": "image/png"}}, "msgtype": "m.sticker", "id": "sha256:426e5551c1aef2d4317ae635811e4e2a6308d2d2ddb0967dc41ef2e72f641214"}, {"body": "349561761", "url": "mxc://seanpai.dev/MlxMROHxmrGZejtFfCyFvLBC", "info": {"w": 256, "h": 213, "size": 123595, "mimetype": "image/png", "thumbnail_url": "mxc://seanpai.dev/MlxMROHxmrGZejtFfCyFvLBC", "thumbnail_info": {"w": 256, "h": 213, "size": 123595, "mimetype": "image/png"}}, "msgtype": "m.sticker", "id": "sha256:96e1072b7a67b6d6c9e3774511588f91bbb07f950fd757f23e0b60fa5ad8e0c6"}, {"body": "349561762", "url": "mxc://seanpai.dev/ruXwRwXQRDkrNntJtYxyLPED", "info": {"w": 256, "h": 176, "size": 103524, "mimetype": "image/png", "thumbnail_url": "mxc://seanpai.dev/ruXwRwXQRDkrNntJtYxyLPED", "thumbnail_info": {"w": 256, "h": 176, "size": 103524, "mimetype": "image/png"}}, "msgtype": "m.sticker", "id": "sha256:0fb60618c9f59a5a0a1a16cd71775c0aeb603fcb296ba5834acfbba3ca5e92fa"}, {"body": "349561763", "url": "mxc://seanpai.dev/rEqMCbFvWJnCiKkBzqcUGust", "info": {"w": 256, "h": 216, "size": 114948, "mimetype": "image/png", "thumbnail_url": "mxc://seanpai.dev/rEqMCbFvWJnCiKkBzqcUGust", "thumbnail_info": {"w": 256, "h": 216, "size": 114948, "mimetype": "image/png"}}, "msgtype": "m.sticker", "id": "sha256:c9225fa7744f15893268a00c8b949ae1f505c64e4ae20925d1e6586428fd4531"}, {"body": "349561764", "url": "mxc://seanpai.dev/iqsyEjHNVzwkepBIGLAfvLRH", "info": {"w": 256, "h": 221, "size": 85376, "mimetype": "image/png", "thumbnail_url": "mxc://seanpai.dev/iqsyEjHNVzwkepBIGLAfvLRH", "thumbnail_info": {"w": 256, "h": 221, "size": 85376, "mimetype": "image/png"}}, "msgtype": "m.sticker", "id": "sha256:e9be2c3352b548a3b7309368f16f5a523fc4a13903cc7795e6a0cc0655346630"}, {"body": "349561765", "url": "mxc://seanpai.dev/LTPDByFLQXungpJhOxrfdEPU", "info": {"w": 256, "h": 202, "size": 114867, "mimetype": "image/png", "thumbnail_url": "mxc://seanpai.dev/LTPDByFLQXungpJhOxrfdEPU", "thumbnail_info": {"w": 256, "h": 202, "size": 114867, "mimetype": "image/png"}}, "msgtype": "m.sticker", "id": "sha256:5f5f3cd26461adbe403fd065c8961f68b058bf84d6c3ce9144dee3e00d32ca80"}, {"body": "349561766", "url": "mxc://seanpai.dev/hKLStxkPgxWhPqbrSAgaPYku", "info": {"w": 256, "h": 195, "size": 166585, "mimetype": "image/png", "thumbnail_url": "mxc://seanpai.dev/hKLStxkPgxWhPqbrSAgaPYku", "thumbnail_info": {"w": 256, "h": 195, "size": 166585, "mimetype": "image/png"}}, "msgtype": "m.sticker", "id": "sha256:df72994dc543e9b952d3cc1f615ea31cfe3e33a45e4796f87c5d554e2e4570c3"}, {"body": "349561767", "url": "mxc://seanpai.dev/wZdEaOojAoOQLHpBRhuZCpox", "info": {"w": 256, "h": 213, "size": 150884, "mimetype": "image/png", "thumbnail_url": "mxc://seanpai.dev/wZdEaOojAoOQLHpBRhuZCpox", "thumbnail_info": {"w": 256, "h": 213, "size": 150884, "mimetype": "image/png"}}, "msgtype": "m.sticker", "id": "sha256:7480fb65f7857c6abb3b31b4ec9e0c1e87b1c98a10f42f6ada4926cd7040f271"}, {"body": "349561768", "url": "mxc://seanpai.dev/GDEbHQXvyGMvSKxAysnBGdwV", "info": {"w": 256, "h": 218, "size": 137660, "mimetype": "image/png", "thumbnail_url": "mxc://seanpai.dev/GDEbHQXvyGMvSKxAysnBGdwV", "thumbnail_info": {"w": 256, "h": 218, "size": 137660, "mimetype": "image/png"}}, "msgtype": "m.sticker", "id": "sha256:2f1f3b6a495302c0b1de43507fae303c21f6804fedbc821660feae74743c9ad9"}, {"body": "349561769", "url": "mxc://seanpai.dev/lrqRFKgKWWRHzUXdLovbTkyE", "info": {"w": 256, "h": 216, "size": 129005, "mimetype": "image/png", "thumbnail_url": "mxc://seanpai.dev/lrqRFKgKWWRHzUXdLovbTkyE", "thumbnail_info": {"w": 256, "h": 216, "size": 129005, "mimetype": "image/png"}}, "msgtype": "m.sticker", "id": "sha256:2d512761c6c2a16f60a0da603b9a45c18fea6fc933c824b675f952d539c7a765"}, {"body": "349561770", "url": "mxc://seanpai.dev/hQJycJTxWBDuXLJytKaxkLEy", "info": {"w": 256, "h": 213, "size": 144586, "mimetype": "image/png", "thumbnail_url": "mxc://seanpai.dev/hQJycJTxWBDuXLJytKaxkLEy", "thumbnail_info": {"w": 256, "h": 213, "size": 144586, "mimetype": "image/png"}}, "msgtype": "m.sticker", "id": "sha256:0aa8dc435732afb4b3c476a1c16bd930be2cf22d5597abf57a1a8f82f454f48d"}, {"body": "349561771", "url": "mxc://seanpai.dev/zlNKYEFFLArHxkutTqsSesFa", "info": {"w": 256, "h": 218, "size": 120891, "mimetype": "image/png", "thumbnail_url": "mxc://seanpai.dev/zlNKYEFFLArHxkutTqsSesFa", "thumbnail_info": {"w": 256, "h": 218, "size": 120891, "mimetype": "image/png"}}, "msgtype": "m.sticker", "id": "sha256:354e32992afe2a3d251ccdc2aef411d7ea5196ac0747f6cbdebf5700f15d1c60"}, {"body": "349561772", "url": "mxc://seanpai.dev/OroRRLDalSoOShjlsdICxKbt", "info": {"w": 256, "h": 213, "size": 123432, "mimetype": "image/png", "thumbnail_url": "mxc://seanpai.dev/OroRRLDalSoOShjlsdICxKbt", "thumbnail_info": {"w": 256, "h": 213, "size": 123432, "mimetype": "image/png"}}, "msgtype": "m.sticker", "id": "sha256:fcbc5f06da4b8ac2b1074b5033811e9036a699d6e28ff579428381f1a004664b"}, {"body": "349561773", "url": "mxc://seanpai.dev/TijOJQLnuFgAdvFLtLpyCWuf", "info": {"w": 256, "h": 159, "size": 103716, "mimetype": "image/png", "thumbnail_url": "mxc://seanpai.dev/TijOJQLnuFgAdvFLtLpyCWuf", "thumbnail_info": {"w": 256, "h": 159, "size": 103716, "mimetype": "image/png"}}, "msgtype": "m.sticker", "id": "sha256:7032eebe733ca735ea5fa93d2c0991a1be56d54b51cf262ab443b1b6f211b255"}]}