{"title": "\u30a2\u30a4\u30c9\u30eb\u30de\u30b9\u30bf\u30fc", "id": "THE_IDOLMASTER", "stickers": [{"body": "32772", "url": "mxc://seanpai.dev/jDQTSlLByCdxeCFMkwBZlPDt", "info": {"w": 256, "h": 198, "size": 43521, "mimetype": "image/png", "thumbnail_url": "mxc://seanpai.dev/jDQTSlLByCdxeCFMkwBZlPDt", "thumbnail_info": {"w": 256, "h": 198, "size": 43521, "mimetype": "image/png"}}, "msgtype": "m.sticker", "id": "sha256:e923d7960dc0b5c7a87608d0d5ff1ddc9bf884df5460eda6ae67b58fa40befc8"}, {"body": "32773", "url": "mxc://seanpai.dev/irtarDGsvEGkTcsVMVenWMWz", "info": {"w": 256, "h": 212, "size": 46036, "mimetype": "image/png", "thumbnail_url": "mxc://seanpai.dev/irtarDGsvEGkTcsVMVenWMWz", "thumbnail_info": {"w": 256, "h": 212, "size": 46036, "mimetype": "image/png"}}, "msgtype": "m.sticker", "id": "sha256:d1e258471706cd890a9ac2a2286e570ae68dcd10a149f62822a1b91334411254"}, {"body": "32774", "url": "mxc://seanpai.dev/rVRYHbZvMrpJcwaTHXmCUEHX", "info": {"w": 244, "h": 256, "size": 37164, "mimetype": "image/png", "thumbnail_url": "mxc://seanpai.dev/rVRYHbZvMrpJcwaTHXmCUEHX", "thumbnail_info": {"w": 244, "h": 256, "size": 37164, "mimetype": "image/png"}}, "msgtype": "m.sticker", "id": "sha256:6d6c4f6aab688b55dc7730b72dc3b70208c2eff993f55d89a0c07247eb6d1684"}, {"body": "32775", "url": "mxc://seanpai.dev/JvmBpnUSJJwVubFENPODCQoi", "info": {"w": 256, "h": 199, "size": 45022, "mimetype": "image/png", "thumbnail_url": "mxc://seanpai.dev/JvmBpnUSJJwVubFENPODCQoi", "thumbnail_info": {"w": 256, "h": 199, "size": 45022, "mimetype": "image/png"}}, "msgtype": "m.sticker", "id": "sha256:224b6398001fdd6162548cda78933bfcf44be369ae93691f9c618161274ac74a"}, {"body": "32776", "url": "mxc://seanpai.dev/oBKRvHLLgTUqNAgjlNEQJcYu", "info": {"w": 256, "h": 207, "size": 40290, "mimetype": "image/png", "thumbnail_url": "mxc://seanpai.dev/oBKRvHLLgTUqNAgjlNEQJcYu", "thumbnail_info": {"w": 256, "h": 207, "size": 40290, "mimetype": "image/png"}}, "msgtype": "m.sticker", "id": "sha256:52542aa5185fa57d5456ae977b8b8a71e8cba9cc7ff99eeef0898145f08fb2d2"}, {"body": "32777", "url": "mxc://seanpai.dev/CGKHCkGSsVzrpzoatFLkSmnG", "info": {"w": 256, "h": 214, "size": 42500, "mimetype": "image/png", "thumbnail_url": "mxc://seanpai.dev/CGKHCkGSsVzrpzoatFLkSmnG", "thumbnail_info": {"w": 256, "h": 214, "size": 42500, "mimetype": "image/png"}}, "msgtype": "m.sticker", "id": "sha256:5386b0bb0c969e0d574f72815b0b42246aea3b086336e4514eb46382cd702bba"}, {"body": "32778", "url": "mxc://seanpai.dev/nwqDNgvZoczQbCuaqnNTZjJc", "info": {"w": 256, "h": 202, "size": 34970, "mimetype": "image/png", "thumbnail_url": "mxc://seanpai.dev/nwqDNgvZoczQbCuaqnNTZjJc", "thumbnail_info": {"w": 256, "h": 202, "size": 34970, "mimetype": "image/png"}}, "msgtype": "m.sticker", "id": "sha256:e31ff8afec5696ff83cb67f8738c7cfdc725ea7f395739f1c4ab1e3f9d0c4895"}, {"body": "32779", "url": "mxc://seanpai.dev/jOoTmyJzNnBKiFMIuhJVSUUT", "info": {"w": 256, "h": 241, "size": 37702, "mimetype": "image/png", "thumbnail_url": "mxc://seanpai.dev/jOoTmyJzNnBKiFMIuhJVSUUT", "thumbnail_info": {"w": 256, "h": 241, "size": 37702, "mimetype": "image/png"}}, "msgtype": "m.sticker", "id": "sha256:521adf97dfa489ca1194f7e908d288b72d1fef5950ddf3e4d9b9f59b9d39b94a"}, {"body": "32780", "url": "mxc://seanpai.dev/aAAEIcQeynIqrjrFhMEHjeNl", "info": {"w": 256, "h": 199, "size": 35767, "mimetype": "image/png", "thumbnail_url": "mxc://seanpai.dev/aAAEIcQeynIqrjrFhMEHjeNl", "thumbnail_info": {"w": 256, "h": 199, "size": 35767, "mimetype": "image/png"}}, "msgtype": "m.sticker", "id": "sha256:c0e834d9001ad37a1dfbc7452e1f67d5dfd57a2debffbf6269a43fee750692ac"}, {"body": "32781", "url": "mxc://seanpai.dev/kWWQHGRATNadqLjEdhSrlEhw", "info": {"w": 256, "h": 219, "size": 37607, "mimetype": "image/png", "thumbnail_url": "mxc://seanpai.dev/kWWQHGRATNadqLjEdhSrlEhw", "thumbnail_info": {"w": 256, "h": 219, "size": 37607, "mimetype": "image/png"}}, "msgtype": "m.sticker", "id": "sha256:c85f3709046782f8e3cce1d1d537ca1068199d93510fe5be828dbef427346a46"}, {"body": "32782", "url": "mxc://seanpai.dev/XbYLsogLWXOgFrJUIfHuCwFa", "info": {"w": 256, "h": 199, "size": 43981, "mimetype": "image/png", "thumbnail_url": "mxc://seanpai.dev/XbYLsogLWXOgFrJUIfHuCwFa", "thumbnail_info": {"w": 256, "h": 199, "size": 43981, "mimetype": "image/png"}}, "msgtype": "m.sticker", "id": "sha256:17afcc749dd3c7f12bdf4518017f21151242cbf6b266a2a8f01b0373ee762065"}, {"body": "32783", "url": "mxc://seanpai.dev/LKIRzmGjajPHxAiTUXAfbqQQ", "info": {"w": 256, "h": 203, "size": 63282, "mimetype": "image/png", "thumbnail_url": "mxc://seanpai.dev/LKIRzmGjajPHxAiTUXAfbqQQ", "thumbnail_info": {"w": 256, "h": 203, "size": 63282, "mimetype": "image/png"}}, "msgtype": "m.sticker", "id": "sha256:7966888bf1fe65d8385942b50a256f76880b296c37be7915b7d0e6d3770158ff"}, {"body": "32784", "url": "mxc://seanpai.dev/tioCLqldMuSlgZkWjGXOMetr", "info": {"w": 222, "h": 256, "size": 38376, "mimetype": "image/png", "thumbnail_url": "mxc://seanpai.dev/tioCLqldMuSlgZkWjGXOMetr", "thumbnail_info": {"w": 222, "h": 256, "size": 38376, "mimetype": "image/png"}}, "msgtype": "m.sticker", "id": "sha256:0ecf2cbf197d4724b53f89349e2792a4e5f9906f428d46a18ad8e472b99fe26a"}, {"body": "32785", "url": "mxc://seanpai.dev/RtZNWdWLrtrWNpicWKSNOZad", "info": {"w": 256, "h": 200, "size": 64035, "mimetype": "image/png", "thumbnail_url": "mxc://seanpai.dev/RtZNWdWLrtrWNpicWKSNOZad", "thumbnail_info": {"w": 256, "h": 200, "size": 64035, "mimetype": "image/png"}}, "msgtype": "m.sticker", "id": "sha256:2580b8e510ba71144b8a5be89661b357152c7ef2a0a2caec9ca0e80be0e4edd5"}, {"body": "32786", "url": "mxc://seanpai.dev/iHBbSTUhJeJXHjatXHVBtllX", "info": {"w": 240, "h": 256, "size": 24589, "mimetype": "image/png", "thumbnail_url": "mxc://seanpai.dev/iHBbSTUhJeJXHjatXHVBtllX", "thumbnail_info": {"w": 240, "h": 256, "size": 24589, "mimetype": "image/png"}}, "msgtype": "m.sticker", "id": "sha256:234f698697f2f1191ef0fba01a1e1215ba0ac870d008e35c22e982dee25a0511"}, {"body": "32787", "url": "mxc://seanpai.dev/uoVCuKretmtZFmUAossOnzOI", "info": {"w": 256, "h": 197, "size": 31494, "mimetype": "image/png", "thumbnail_url": "mxc://seanpai.dev/uoVCuKretmtZFmUAossOnzOI", "thumbnail_info": {"w": 256, "h": 197, "size": 31494, "mimetype": "image/png"}}, "msgtype": "m.sticker", "id": "sha256:f4f67e54aaca93dbc24c4bf05d89c53307808c3f5dd89c23576f9f19dcf13f75"}, {"body": "32788", "url": "mxc://seanpai.dev/BMqdeAvWaCoWvDEmzyEKHCZB", "info": {"w": 256, "h": 207, "size": 44959, "mimetype": "image/png", "thumbnail_url": "mxc://seanpai.dev/BMqdeAvWaCoWvDEmzyEKHCZB", "thumbnail_info": {"w": 256, "h": 207, "size": 44959, "mimetype": "image/png"}}, "msgtype": "m.sticker", "id": "sha256:e4fe71e173d5c7630b0be30e4021c663335146c5d09c9b83258bb4d5849e2621"}, {"body": "32789", "url": "mxc://seanpai.dev/gzRgawnByfoyuyVyLqqCXxmz", "info": {"w": 256, "h": 215, "size": 42835, "mimetype": "image/png", "thumbnail_url": "mxc://seanpai.dev/gzRgawnByfoyuyVyLqqCXxmz", "thumbnail_info": {"w": 256, "h": 215, "size": 42835, "mimetype": "image/png"}}, "msgtype": "m.sticker", "id": "sha256:84ab895f5d4b5660b47c5d83885b33a2cc82ddeaf16c6397172cb7c96a1d4188"}, {"body": "32790", "url": "mxc://seanpai.dev/dMhqjdnpXFXBiSofJFwiXavN", "info": {"w": 256, "h": 254, "size": 32562, "mimetype": "image/png", "thumbnail_url": "mxc://seanpai.dev/dMhqjdnpXFXBiSofJFwiXavN", "thumbnail_info": {"w": 256, "h": 254, "size": 32562, "mimetype": "image/png"}}, "msgtype": "m.sticker", "id": "sha256:12afb55cde2e2d8107d7c37d5d2eca4d64eec93146fcd5eb51bc0ac1008e3d1e"}, {"body": "32791", "url": "mxc://seanpai.dev/mmBBiQFQhITmHHmHERFJXHYN", "info": {"w": 256, "h": 228, "size": 40748, "mimetype": "image/png", "thumbnail_url": "mxc://seanpai.dev/mmBBiQFQhITmHHmHERFJXHYN", "thumbnail_info": {"w": 256, "h": 228, "size": 40748, "mimetype": "image/png"}}, "msgtype": "m.sticker", "id": "sha256:6837771bf1c19c3fd2c023a686efd523c1eba3530cccbd1933e59a33945039be"}, {"body": "32792", "url": "mxc://seanpai.dev/NpetUQaHHWgTjoyQVZyZFSKZ", "info": {"w": 256, "h": 205, "size": 84619, "mimetype": "image/png", "thumbnail_url": "mxc://seanpai.dev/NpetUQaHHWgTjoyQVZyZFSKZ", "thumbnail_info": {"w": 256, "h": 205, "size": 84619, "mimetype": "image/png"}}, "msgtype": "m.sticker", "id": "sha256:9c82b6e159acde638e421c5b614ffe30410ce312e71578290dd836d2e5df9ecf"}, {"body": "32793", "url": "mxc://seanpai.dev/WLZdBeqJZatngCZdBerCmdVV", "info": {"w": 256, "h": 206, "size": 51278, "mimetype": "image/png", "thumbnail_url": "mxc://seanpai.dev/WLZdBeqJZatngCZdBerCmdVV", "thumbnail_info": {"w": 256, "h": 206, "size": 51278, "mimetype": "image/png"}}, "msgtype": "m.sticker", "id": "sha256:35680c95e46c86e70024f971e1282671e9c523cd7f295588a6fa7861420df97a"}, {"body": "32794", "url": "mxc://seanpai.dev/wKcjYyNLGavCMEQTnFowPTXE", "info": {"w": 256, "h": 218, "size": 29799, "mimetype": "image/png", "thumbnail_url": "mxc://seanpai.dev/wKcjYyNLGavCMEQTnFowPTXE", "thumbnail_info": {"w": 256, "h": 218, "size": 29799, "mimetype": "image/png"}}, "msgtype": "m.sticker", "id": "sha256:34906fa930dbd97459ab97fa5c42b5da84056c7de470cd239d9de470073a0ed3"}, {"body": "32795", "url": "mxc://seanpai.dev/JDqePlZIvvasPtbPQiRgfDii", "info": {"w": 256, "h": 204, "size": 39154, "mimetype": "image/png", "thumbnail_url": "mxc://seanpai.dev/JDqePlZIvvasPtbPQiRgfDii", "thumbnail_info": {"w": 256, "h": 204, "size": 39154, "mimetype": "image/png"}}, "msgtype": "m.sticker", "id": "sha256:d15e6b051b6f3f05192b2d2c40eb25149e5d18bcc8eca07f755a0634686afc96"}, {"body": "32796", "url": "mxc://seanpai.dev/iiWTMMXPdgPwnAkYyAsCCtMj", "info": {"w": 256, "h": 192, "size": 48060, "mimetype": "image/png", "thumbnail_url": "mxc://seanpai.dev/iiWTMMXPdgPwnAkYyAsCCtMj", "thumbnail_info": {"w": 256, "h": 192, "size": 48060, "mimetype": "image/png"}}, "msgtype": "m.sticker", "id": "sha256:53f61be1e90129779faa333052f83fa800c30bfde0a2991017e5e2f8b6dbfc3a"}, {"body": "32797", "url": "mxc://seanpai.dev/LIvmNpxdDZYVsVMMnRyyAOiJ", "info": {"w": 256, "h": 203, "size": 36162, "mimetype": "image/png", "thumbnail_url": "mxc://seanpai.dev/LIvmNpxdDZYVsVMMnRyyAOiJ", "thumbnail_info": {"w": 256, "h": 203, "size": 36162, "mimetype": "image/png"}}, "msgtype": "m.sticker", "id": "sha256:b33062a8a86a88f6a7671ebb1607c203f316f22fb1945228ccf960f1156c10cb"}, {"body": "32798", "url": "mxc://seanpai.dev/ioWzrnYtFYUMsOPCSglCmvXd", "info": {"w": 256, "h": 249, "size": 27166, "mimetype": "image/png", "thumbnail_url": "mxc://seanpai.dev/ioWzrnYtFYUMsOPCSglCmvXd", "thumbnail_info": {"w": 256, "h": 249, "size": 27166, "mimetype": "image/png"}}, "msgtype": "m.sticker", "id": "sha256:a31fbebf13d37d27e2e592220438efdf0687c3bd30844ff84e705744c8ae140e"}, {"body": "32799", "url": "mxc://seanpai.dev/BeZubnoRvmqbaYslbPomrhYa", "info": {"w": 256, "h": 199, "size": 34772, "mimetype": "image/png", "thumbnail_url": "mxc://seanpai.dev/BeZubnoRvmqbaYslbPomrhYa", "thumbnail_info": {"w": 256, "h": 199, "size": 34772, "mimetype": "image/png"}}, "msgtype": "m.sticker", "id": "sha256:0ca2a05fb72cecc38ac6958b7fc1b71f6d7222c8bf757820491597e7a59a28a6"}, {"body": "32800", "url": "mxc://seanpai.dev/LBUNeRbzJsBqEaaEpryUFZAc", "info": {"w": 256, "h": 203, "size": 59356, "mimetype": "image/png", "thumbnail_url": "mxc://seanpai.dev/LBUNeRbzJsBqEaaEpryUFZAc", "thumbnail_info": {"w": 256, "h": 203, "size": 59356, "mimetype": "image/png"}}, "msgtype": "m.sticker", "id": "sha256:298e6276b93fc99ff323302d6faeb4b268a8de50f1f29ca1883125db402cabca"}, {"body": "32801", "url": "mxc://seanpai.dev/MjdtJlPrqgMIpJlQhPzJVgtf", "info": {"w": 256, "h": 202, "size": 62812, "mimetype": "image/png", "thumbnail_url": "mxc://seanpai.dev/MjdtJlPrqgMIpJlQhPzJVgtf", "thumbnail_info": {"w": 256, "h": 202, "size": 62812, "mimetype": "image/png"}}, "msgtype": "m.sticker", "id": "sha256:3ba7c0e22392b21cd1fe276679f45bc26d9f2c46f7d1d7b241a38064dc347337"}, {"body": "32802", "url": "mxc://seanpai.dev/YRnYFrZNjcgpoVUlRNmeOeKu", "info": {"w": 256, "h": 201, "size": 43871, "mimetype": "image/png", "thumbnail_url": "mxc://seanpai.dev/YRnYFrZNjcgpoVUlRNmeOeKu", "thumbnail_info": {"w": 256, "h": 201, "size": 43871, "mimetype": "image/png"}}, "msgtype": "m.sticker", "id": "sha256:c49d7cb701c50afcf7c218d5fa6463cb862e037ccc9a4bbf7992b1b1ffc749d7"}, {"body": "32803", "url": "mxc://seanpai.dev/NvvTbhOKPDTluKmioanjDXga", "info": {"w": 256, "h": 208, "size": 41743, "mimetype": "image/png", "thumbnail_url": "mxc://seanpai.dev/NvvTbhOKPDTluKmioanjDXga", "thumbnail_info": {"w": 256, "h": 208, "size": 41743, "mimetype": "image/png"}}, "msgtype": "m.sticker", "id": "sha256:f823276a7de5cc155c90955ced2c5d5996f444294c7135d7066e34a4268c55a7"}, {"body": "32804", "url": "mxc://seanpai.dev/joNTELmDdQTduLrRhfTjsYKF", "info": {"w": 256, "h": 230, "size": 37796, "mimetype": "image/png", "thumbnail_url": "mxc://seanpai.dev/joNTELmDdQTduLrRhfTjsYKF", "thumbnail_info": {"w": 256, "h": 230, "size": 37796, "mimetype": "image/png"}}, "msgtype": "m.sticker", "id": "sha256:34b0845ddf1b4eb6ce2841c5b3a80cc5ffea502b3f1bfcfce4af42bf2612e9f0"}, {"body": "32805", "url": "mxc://seanpai.dev/iBazEGxbhECFamnAJEnaFuzB", "info": {"w": 256, "h": 212, "size": 39973, "mimetype": "image/png", "thumbnail_url": "mxc://seanpai.dev/iBazEGxbhECFamnAJEnaFuzB", "thumbnail_info": {"w": 256, "h": 212, "size": 39973, "mimetype": "image/png"}}, "msgtype": "m.sticker", "id": "sha256:2b3df3e06c4425feb33ca0d0db5b3c49b026be1f6824eee17d3cce6454994f76"}, {"body": "32806", "url": "mxc://seanpai.dev/EBNlXpPSmzDgDWaVbVTpaUKW", "info": {"w": 256, "h": 234, "size": 44861, "mimetype": "image/png", "thumbnail_url": "mxc://seanpai.dev/EBNlXpPSmzDgDWaVbVTpaUKW", "thumbnail_info": {"w": 256, "h": 234, "size": 44861, "mimetype": "image/png"}}, "msgtype": "m.sticker", "id": "sha256:b7d1d0ea9c1aa1a4bbd3f50983ea85d240c39b6738b5d4f58076c55710a221b4"}, {"body": "32807", "url": "mxc://seanpai.dev/OmhGgnqflHYEcAIRBlsoGnUT", "info": {"w": 256, "h": 200, "size": 35984, "mimetype": "image/png", "thumbnail_url": "mxc://seanpai.dev/OmhGgnqflHYEcAIRBlsoGnUT", "thumbnail_info": {"w": 256, "h": 200, "size": 35984, "mimetype": "image/png"}}, "msgtype": "m.sticker", "id": "sha256:3cdf6dd96ad1fc1068404492fd8c73275fab52f23c4b4c83d0c70f0644d6dd43"}, {"body": "32808", "url": "mxc://seanpai.dev/GtXCzNPuYDAmEweeMMGEKDKE", "info": {"w": 256, "h": 235, "size": 33880, "mimetype": "image/png", "thumbnail_url": "mxc://seanpai.dev/GtXCzNPuYDAmEweeMMGEKDKE", "thumbnail_info": {"w": 256, "h": 235, "size": 33880, "mimetype": "image/png"}}, "msgtype": "m.sticker", "id": "sha256:d5129c767cf99e11a6b7ab815114f3f1f0c4b66141e060a557bc10a476dbc920"}, {"body": "32809", "url": "mxc://seanpai.dev/bAxdFOeZJZfieEBrCapKtylr", "info": {"w": 256, "h": 206, "size": 53481, "mimetype": "image/png", "thumbnail_url": "mxc://seanpai.dev/bAxdFOeZJZfieEBrCapKtylr", "thumbnail_info": {"w": 256, "h": 206, "size": 53481, "mimetype": "image/png"}}, "msgtype": "m.sticker", "id": "sha256:1b9ee1d129bea5bb6d39341558b3b62e67afb160e500c431c9c4839540d95da1"}, {"body": "32810", "url": "mxc://seanpai.dev/NFdLcLHmvYdPkvqVylqsZpcv", "info": {"w": 256, "h": 232, "size": 30299, "mimetype": "image/png", "thumbnail_url": "mxc://seanpai.dev/NFdLcLHmvYdPkvqVylqsZpcv", "thumbnail_info": {"w": 256, "h": 232, "size": 30299, "mimetype": "image/png"}}, "msgtype": "m.sticker", "id": "sha256:3e9ef1f90e79e0bd79c7c4a3f85701431ae999bf678d80af79ba5441d0beabc0"}, {"body": "32811", "url": "mxc://seanpai.dev/JrMYhrfPyQRowVjNhjKHdksM", "info": {"w": 256, "h": 206, "size": 46863, "mimetype": "image/png", "thumbnail_url": "mxc://seanpai.dev/JrMYhrfPyQRowVjNhjKHdksM", "thumbnail_info": {"w": 256, "h": 206, "size": 46863, "mimetype": "image/png"}}, "msgtype": "m.sticker", "id": "sha256:18127a9fa90051c53fa28bc47d973ca2a56f3cf4e1441d5b710fd36b16096b44"}]}